cymple/__init__.py
cymple/__main__.py
cymple/builder.py
cymple/table_model.py
cymple/typedefs.py
cymple/version.py
cymple_kuzu-0.0.7.dist-info/licenses/LICENSE
cymple_kuzu-0.0.7.dist-info/METADATA
cymple_kuzu-0.0.7.dist-info/WHEEL
cymple_kuzu-0.0.7.dist-info/top_level.txt
cymple_kuzu-0.0.7.dist-info/RECORD
