Metadata-Version: 2.4
Name: cymple_kuzu
Version: 0.0.7
Summary: A productivity enhancer for creating Cypher queries in Python
Requires-Python: >=3.9
License-File: LICENSE
Dynamic: license-file
